odincontrib/__init__.py
odincontrib/sqlalchemy/__init__.py
odincontrib.sqlalchemy-0.3.0.dist-info/DESCRIPTION.rst
odincontrib.sqlalchemy-0.3.0.dist-info/METADATA
odincontrib.sqlalchemy-0.3.0.dist-info/RECORD
odincontrib.sqlalchemy-0.3.0.dist-info/WHEEL
odincontrib.sqlalchemy-0.3.0.dist-info/metadata.json
odincontrib.sqlalchemy-0.3.0.dist-info/pbr.json
odincontrib.sqlalchemy-0.3.0.dist-info/top_level.txt
